LICENSE
MANIFEST.in
README.rst
requirements.txt
setup.py
version.py
libcloud_vagrant.egg-info/PKG-INFO
libcloud_vagrant.egg-info/SOURCES.txt
libcloud_vagrant.egg-info/dependency_links.txt
libcloud_vagrant.egg-info/entry_points.txt
libcloud_vagrant.egg-info/not-zip-safe
libcloud_vagrant.egg-info/requires.txt
libcloud_vagrant.egg-info/top_level.txt
libcloudvagrant/__init__.py
libcloudvagrant/common/__init__.py
libcloudvagrant/common/ca-bundle.crt
libcloudvagrant/common/catalogue.py
libcloudvagrant/common/cmd.py
libcloudvagrant/common/types.py
libcloudvagrant/common/virtualbox.py
libcloudvagrant/common/templates/Vagrantfile
libcloudvagrant/common/templates/__init__.py
libcloudvagrant/compute/__init__.py
libcloudvagrant/compute/driver.py
libcloudvagrant/compute/types.py
libcloudvagrant/tests/__init__.py
libcloudvagrant/tests/conftest.py
libcloudvagrant/tests/test_catalogue.py
libcloudvagrant/tests/test_deploy.py
libcloudvagrant/tests/test_extensions.py
libcloudvagrant/tests/test_images.py
libcloudvagrant/tests/test_libcloud.py
libcloudvagrant/tests/test_network.py
libcloudvagrant/tests/test_nodes.py
libcloudvagrant/tests/test_types.py
libcloudvagrant/tests/test_volumes.py