Metadata-Version: 1.1
Name: libcloud-vagrant
Version: 0.5.0
Summary: A libcloud compute provider for local Vagrant boxes
Home-page: https://github.com/carletes/libcloud-vagrant
Author: Carlos Valiente
Author-email: carlos@pepelabs.net
License: MIT
Platform: UNKNOWN
Classifier: Development Status :: 4 - Beta
Classifier: Environment :: Console
Classifier: Intended Audience :: System Administrators
Classifier: License :: OSI Approved :: MIT License
Classifier: Operating System :: OS Independent
Classifier: Topic :: Software Development :: Libraries :: Python Modules
Classifier: Programming Language :: Python
Classifier: Programming Language :: Python :: 2.7
